bbtt/__init__.py
bbtt/__main__.py
bbtt/coord/__init__.py
bbtt/coord/__main__.py
2b2t-0.3.0.dist-info/LICENSE
2b2t-0.3.0.dist-info/METADATA
2b2t-0.3.0.dist-info/WHEEL
2b2t-0.3.0.dist-info/entry_points.txt
2b2t-0.3.0.dist-info/top_level.txt
2b2t-0.3.0.dist-info/RECORD
