Metadata-Version: 2.1
Name: 2b2t
Version: 0.3.0
Summary: A 2b2t toolbox.
Home-page: https://github.com/keuin/2b2t
Author: Keuin
Author-email: keuinx@gmail.com
License: MIT
Platform: UNKNOWN
Classifier: License :: OSI Approved :: MIT License
Classifier: Programming Language :: Python :: 3
License-File: LICENSE
Requires-Dist: mcstatus
